{
    "_fv": 24,
    "_type": "recipe",
    "definition": {
      "recipeType": "Crafting",
      "xpReward": 0.0,
      "cookingTime": 200,
      "recipeRetstackSize": 1,
      "group": "block",
      "recipeShapeless": false,
      "recipeSlots": [
        {
          "value": ""
        },
        {
          "value": ""
        },
        {
          "value": ""
        },

        {
          "value": ""
        },
        {
          "value": "Items.WHEAT_SEEDS"
        },
        {
          "value": ""
        },

        {
          "value": ""
        },
        {
          "value": "Blocks.DIRT"
        },
        {
          "value": ""
        }
      ],
      "recipeReturnStack": {
        "value": "Blocks.GRASS_BLOCK"
      },
      "name": "grass_recipe",
      "namespace": "mod"
    }
  }